call_context_lib/__init__.py
call_context_lib/base.py
call_context_lib/core.py
call_context_lib/logger.py
call_context_lib-0.2.6.dist-info/METADATA
call_context_lib-0.2.6.dist-info/WHEEL
call_context_lib-0.2.6.dist-info/licenses/LICENSE
call_context_lib-0.2.6.dist-info/RECORD
