Metadata-Version: 2.4
Name: call-context-lib
Version: 0.2.6
Summary: A context management library for Python applications with callback support
Project-URL: Homepage, https://github.com/jitokim/call-context-lib
Project-URL: Bug Tracker, https://github.com/jitokim/call-context-lib/issues
Project-URL: Repository, https://github.com/jitokim/call-context-lib
Project-URL: Documentation, https://jitokim.github.io/call-context-lib
Author-email: Jihoon Kim <pigberger70@gmail.com>
Maintainer-email: Jihoon Kim <pigberger70@gmail.com>
License: MIT
License-File: LICENSE
Keywords: callback,context,context-management,library,python
Classifier: Development Status :: 4 - Beta
Classifier: Intended Audience :: Developers
Classifier: License :: OSI Approved :: MIT License
Classifier: Operating System :: OS Independent
Classifier: Programming Language :: Python :: 3.9
Classifier: Programming Language :: Python :: 3.10
Classifier: Programming Language :: Python :: 3.11
Classifier: Programming Language :: Python :: 3.12
Classifier: Topic :: Software Development :: Libraries :: Python Modules
Classifier: Topic :: Software Development :: Quality Assurance
Classifier: Typing :: Typed
Requires-Python: >=3.9
Requires-Dist: bandit>=1.7.0
Requires-Dist: build>=0.10.0
Requires-Dist: pip-audit>=2.7.0
Requires-Dist: pre-commit>=3.0
Requires-Dist: pytest-asyncio>=0.21.0
Requires-Dist: pytest-cov>=4.0
Requires-Dist: pytest-mock>=3.10.0
Requires-Dist: pytest>=7.0
Requires-Dist: ruff>=0.1.0
Requires-Dist: setuptools>=78.1.1
Requires-Dist: twine>=4.0.0
